LICENSE
MANIFEST.in
README
aws-ec2-assign-elastic-ip
setup.py
aws_ec2_assign_elastic_ip/__init__.py
aws_ec2_assign_elastic_ip/command_line_options.py
aws_ec2_assign_elastic_ip/logging.conf
aws_ec2_assign_elastic_ip/settings.conf
aws_ec2_assign_elastic_ip.egg-info/PKG-INFO
aws_ec2_assign_elastic_ip.egg-info/SOURCES.txt
aws_ec2_assign_elastic_ip.egg-info/dependency_links.txt
aws_ec2_assign_elastic_ip.egg-info/not-zip-safe
aws_ec2_assign_elastic_ip.egg-info/requires.txt
aws_ec2_assign_elastic_ip.egg-info/top_level.txt
aws_ec2_assign_elastic_ip/__pycache__/__init__.cpython-36.pyc
aws_ec2_assign_elastic_ip/__pycache__/command_line_options.cpython-36.pyc