Metadata-Version: 1.1
Name: aws-ec2-assign-elastic-ip
Version: 0.8.0
Summary: Automatically assign Elastic IPs to AWS EC2 instances
Home-page: https://github.com/skymill/aws-ec2-assign-elastic-ip
Author: Sebastian Dahlgren, Skymill Solutions
Author-email: sebastian.dahlgren@skymill.se
License: Apache License, Version 2.0
Keywords: aws amazon web services ec2 as elasticip eip
Platform: Any
Classifier: Development Status :: 4 - Beta
Classifier: Environment :: Console
Classifier: License :: OSI Approved :: Apache Software License
Classifier: Operating System :: OS Independent
Classifier: Programming Language :: Python
